<annotation>
	<folder>portrait</folder>
	<filename>DJI_0016.jpg</filename>
	<path>/home/jetbot/foodbankPhotos/portrait/DJI_0016.jpg</path>
	<source>
		<database>Unknown</database>
	</source>
	<size>
		<width>3024</width>
		<height>4032</height>
		<depth>3</depth>
	</size>
	<segmented>0</segmented>
	<object>
		<name>empty</name>
		<pose>Unspecified</pose>
		<truncated>0</truncated>
		<difficult>0</difficult>
		<bndbox>
			<xmin>464</xmin>
			<ymin>2960</ymin>
			<xmax>1520</xmax>
			<ymax>3544</ymax>
		</bndbox>
	</object>
	<object>
		<name>empty</name>
		<pose>Unspecified</pose>
		<truncated>0</truncated>
		<difficult>0</difficult>
		<bndbox>
			<xmin>1556</xmin>
			<ymin>2980</ymin>
			<xmax>2636</xmax>
			<ymax>3532</ymax>
		</bndbox>
	</object>
	<object>
		<name>empty</name>
		<pose>Unspecified</pose>
		<truncated>0</truncated>
		<difficult>0</difficult>
		<bndbox>
			<xmin>816</xmin>
			<ymin>2656</ymin>
			<xmax>1532</xmax>
			<ymax>2912</ymax>
		</bndbox>
	</object>
	<object>
		<name>empty</name>
		<pose>Unspecified</pose>
		<truncated>0</truncated>
		<difficult>0</difficult>
		<bndbox>
			<xmin>1584</xmin>
			<ymin>2664</ymin>
			<xmax>2340</xmax>
			<ymax>2964</ymax>
		</bndbox>
	</object>
</annotation>
